{
    "keep": {
        "days": true,
        "amount": 14
    },
    "auditLog": "D:\\Job-Projects\\university-management-service\\logs\\winston\\errors\\.51b1f5dfbdd6d7207f182c433d669adc264fca1c-audit.json",
    "files": [
        {
            "date": 1733639626569,
            "name": "D:\\Job-Projects\\university-management-service\\logs\\winston\\errors\\phu-2024-12-08-12-error.log",
            "hash": "9a3147e7c2e1b4f868deb2b377074c4a0ebad93bf48161ad4c3ba0204c5d1a4e"
        },
        {
            "date": 1733895149433,
            "name": "D:\\Job-Projects\\university-management-service\\logs\\winston\\errors\\phu-2024-12-11-11-error.log",
            "hash": "ca553aa3c56f8418d80687caf05c00a2bb27a03f57acf032267e40da4fb12310"
        },
        {
            "date": 1734169888339,
            "name": "D:\\Job-Projects\\university-management-service\\logs\\winston\\errors\\phu-2024-12-14-15-error.log",
            "hash": "d442ee442504c955b4579c938506bf8c5fd0db846346761f5a6aa4e44f0e6401"
        },
        {
            "date": 1734174310035,
            "name": "D:\\Job-Projects\\university-management-service\\logs\\winston\\errors\\phu-2024-12-14-17-error.log",
            "hash": "98062920c3664a9e568e71fe526dd5d06cd0d3d41b97baa8a54a75dd8f32eb7e"
        },
        {
            "date": 1734180955372,
            "name": "D:\\Job-Projects\\university-management-service\\logs\\winston\\errors\\phu-2024-12-14-18-error.log",
            "hash": "d9498fe2b1852a8f93981df68bd91a474e9db01b9cfc40336e64c4107eee7572"
        },
        {
            "date": 1734182731230,
            "name": "D:\\Job-Projects\\university-management-service\\logs\\winston\\errors\\phu-2024-12-14-19-error.log",
            "hash": "07fd46f261aca6bf31f037d5caeeec042937f976d349873636378046ebfc2a8a"
        },
        {
            "date": 1734331086531,
            "name": "D:\\Job-Projects\\university-management-service\\logs\\winston\\errors\\phu-2024-12-16-12-error.log",
            "hash": "58aeaab149db29fc59f8a0524045af0032c48981dce36aa8cd7bb5b6eb2e111a"
        },
        {
            "date": 1734332900036,
            "name": "D:\\Job-Projects\\university-management-service\\logs\\winston\\errors\\phu-2024-12-16-13-error.log",
            "hash": "6e7f9ebd8655a647b225c13d9996b7d77ca18d3a53048da9aa8663aeb85895c9"
        },
        {
            "date": 1734340691648,
            "name": "D:\\Job-Projects\\university-management-service\\logs\\winston\\errors\\phu-2024-12-16-15-error.log",
            "hash": "623e3d43e392a6e95ea169ddb302ebe60e326734a5b3b965895415a4fd08a6ea"
        }
    ],
    "hashType": "sha256"
}